{
    "qvalue" : {
        "ARCHITECTURE" : [
            400,
            300
        ],
        "INIT": "naive",
        "ACTIVATION" : "ReLU",
        "LEARNING_RATE": 1e-3,
        "TAU": 5e-3,
        "WEIGHT_DECAY": 0.0,
        "DROPOUT": false,
        "BATCHNORM": false
    },
    "policy" : {
        "ARCHITECTURE" : [
            400,
            300
        ],
        "INIT": "naive",
        "ACTIVATION" : "ReLU",
        "LEARNING_RATE": 1e-3,
        "WEIGHT_DECAY": 0.0,
        "DROPOUT": false,
        "BATCHNORM": false,
        "CEM_ITERATIONS": 2,
        "CEM_BATCH": 64,
        "CEM_TOPK": 6
    },
    "MEMORY_SIZE": 1e6,
    "BATCH_SIZE": 100,
    "UPDATE_STEPS": 1,
    "GAMMA": 0.99,
    "POLICY_EXPLORATION_NOISE": 0,
    "POLICY_UPDATE_NOISE":0.0,
    "POLICY_CLIP": 0.5,
    "POLICY_UPDATE_FREQ" : 1,
    "evaluation": {
        "avaraging_window": 20,
        "disturbance_intervall": 10,
        "eval_episodes": 10,
        "eval_timesteps": 5000,
        "max_external_force": 1,
        "total_timesteps": 1000000.0
    }
}
